pubmed_lib/__init__.py
pubmed_lib/_modidx.py
pubmed_lib/affiliation.py
pubmed_lib/author.py
pubmed_lib/core.py
pubmed_lib/data.py
pubmed_lib/parser.py
pubmed_lib/result.py
pubmed_lib/search.py
pubmed_lib/viz.py
pubmed_lib-0.0.2.dist-info/LICENSE
pubmed_lib-0.0.2.dist-info/METADATA
pubmed_lib-0.0.2.dist-info/WHEEL
pubmed_lib-0.0.2.dist-info/entry_points.txt
pubmed_lib-0.0.2.dist-info/top_level.txt
pubmed_lib-0.0.2.dist-info/RECORD
