Metadata-Version: 2.1
Name: pubmed-lib
Version: 0.0.2
Summary: Simple wrapper for pubmed resutls
Home-page: https://github.com/Dmaturana81/pubmed_lib
Author: Dmaturana81
Author-email: elmaturana@gmail.com
License: Apache Software License 2.0
Keywords: nbdev jupyter notebook python
Classifier: Development Status :: 4 - Beta
Classifier: Intended Audience :: Developers
Classifier: Natural Language :: English
Classifier: Programming Language :: Python :: 3.7
Classifier: Programming Language :: Python :: 3.8
Classifier: Programming Language :: Python :: 3.9
Classifier: Programming Language :: Python :: 3.10
Classifier: License :: OSI Approved :: Apache Software License
Requires-Python: >=3.7
License-File: LICENSE
Requires-Dist: nbdev
Requires-Dist: fastcore
Requires-Dist: pydantic
Requires-Dist: biopython
Requires-Dist: pandas
Requires-Dist: seaborn
Requires-Dist: plotly
Requires-Dist: matplotlib
Requires-Dist: numpy
Requires-Dist: python-dotenv
Requires-Dist: pubmed-lib
Provides-Extra: dev
